Metadata-Version: 2.1
Name: printfuldebug
Version: 1.0.0
Summary: print() but for nerds.
Home-page: UNKNOWN
Author: yuma061
Author-email: 
License: UNKNOWN
Keywords: python,print
Platform: UNKNOWN
Classifier: Intended Audience :: Developers
Classifier: Programming Language :: Python :: 3
Classifier: Operating System :: Microsoft :: Windows
